LICENSE.txt
MANIFEST.in
README.md
requirements.txt
setup.py
lamarck/__init__.py
lamarck/explorer.py
lamarck/optimizer.py
lamarck/population.py
lamarck/rankcalculator.py
lamarck/reproduce.py
lamarck/simconfig.py
lamarck/utils.py
lamarck/version.py
lamarck.egg-info/PKG-INFO
lamarck.egg-info/SOURCES.txt
lamarck.egg-info/dependency_links.txt
lamarck.egg-info/requires.txt
lamarck.egg-info/top_level.txt
lamarck/genes/__init__.py
lamarck/genes/gene.py
lamarck/genes/mixer.py