Metadata-Version: 2.1
Name: lamarck
Version: 0.2.0
Summary: Genetic Algorithm Prototype.
Home-page: https://github.com/vczoni/lamarck
Author: Victor Zoni
Author-email: vczoni@gmail.com
License: MIT
Download-URL: https://github.com/vczoni/lamarck/archive/v0.2.0.tar.gz
Keywords: GENETIC,ALGORITHM,GA,BASIC,GENERAL,OPTIMIZATION,SIMULATION
Platform: UNKNOWN
Classifier: Development Status :: 3 - Alpha
Classifier: Intended Audience :: Developers
Classifier: Topic :: Software Development :: Build Tools
Classifier: License :: OSI Approved :: MIT License
Classifier: Programming Language :: Python :: 3
Requires-Python: >=3
License-File: LICENSE.txt
